nifreeze/__init__.py
nifreeze/__main__.py
nifreeze/_version.py
nifreeze/conftest.py
nifreeze/estimator.py
nifreeze/exceptions.py
nifreeze/py.typed
nifreeze/analysis/__init__.py
nifreeze/analysis/filtering.py
nifreeze/analysis/measure_agreement.py
nifreeze/analysis/motion.py
nifreeze/cli/__init__.py
nifreeze/cli/parser.py
nifreeze/cli/run.py
nifreeze/data/__init__.py
nifreeze/data/base.py
nifreeze/data/dmri.py
nifreeze/data/filtering.py
nifreeze/data/pet.py
nifreeze/data/splitting.py
nifreeze/data/utils.py
nifreeze/model/__init__.py
nifreeze/model/_dipy.py
nifreeze/model/base.py
nifreeze/model/dmri.py
nifreeze/model/gpr.py
nifreeze/model/gqi.py
nifreeze/model/pet.py
nifreeze/registration/__init__.py
nifreeze/registration/ants.py
nifreeze/registration/utils.py
nifreeze/registration/config/b0-to-b0_level0.json
nifreeze/registration/config/dwi-to-b0_level0.json
nifreeze/registration/config/dwi-to-dwi_level0.json
nifreeze/registration/config/dwi-to-dwi_level1.json
nifreeze/registration/config/pet-to-pet_level1.json
nifreeze/testing/__init__.py
nifreeze/testing/simulations.py
nifreeze/utils/__init__.py
nifreeze/utils/iterators.py
nifreeze/utils/ndimage.py
nifreeze/viz/__init__.py
nifreeze/viz/bland_altman.py
nifreeze/viz/motion_viz.py
nifreeze/viz/signals.py
nifreeze-25.0.0.dev456.dist-info/METADATA
nifreeze-25.0.0.dev456.dist-info/WHEEL
nifreeze-25.0.0.dev456.dist-info/entry_points.txt
nifreeze-25.0.0.dev456.dist-info/licenses/LICENSE
nifreeze-25.0.0.dev456.dist-info/licenses/NOTICE
nifreeze-25.0.0.dev456.dist-info/RECORD
